README.md
setup.py
MatchZoo_test.egg-info/PKG-INFO
MatchZoo_test.egg-info/SOURCES.txt
MatchZoo_test.egg-info/dependency_links.txt
MatchZoo_test.egg-info/requires.txt
MatchZoo_test.egg-info/top_level.txt
matchzoo/__init__.py
matchzoo/version.py
matchzoo/auto/__init__.py
matchzoo/auto/preparer/__init__.py
matchzoo/auto/preparer/prepare.py
matchzoo/auto/preparer/preparer.py
matchzoo/auto/tuner/__init__.py
matchzoo/auto/tuner/tune.py
matchzoo/auto/tuner/tuner.py
matchzoo/data_pack/__init__.py
matchzoo/data_pack/data_pack.py
matchzoo/data_pack/pack.py
matchzoo/dataloader/__init__.py
matchzoo/dataloader/dataloader.py
matchzoo/dataloader/dataloader_builder.py
matchzoo/dataloader/dataset.py
matchzoo/dataloader/dataset_builder.py
matchzoo/dataloader/sampler.py
matchzoo/dataloader/callbacks/__init__.py
matchzoo/dataloader/callbacks/dynamic_pooling.py
matchzoo/dataloader/callbacks/histogram.py
matchzoo/dataloader/callbacks/lambda_callback.py
matchzoo/dataloader/callbacks/padding.py
matchzoo/datasets/__init__.py
matchzoo/datasets/embeddings/__init__.py
matchzoo/datasets/embeddings/load_fasttext_embedding.py
matchzoo/datasets/embeddings/load_glove_embedding.py
matchzoo/datasets/quora_qp/__init__.py
matchzoo/datasets/quora_qp/load_data.py
matchzoo/datasets/snli/__init__.py
matchzoo/datasets/snli/load_data.py
matchzoo/datasets/toy/__init__.py
matchzoo/datasets/wiki_qa/__init__.py
matchzoo/datasets/wiki_qa/load_data.py
matchzoo/embedding/__init__.py
matchzoo/embedding/embedding.py
matchzoo/engine/__init__.py
matchzoo/engine/base_callback.py
matchzoo/engine/base_metric.py
matchzoo/engine/base_model.py
matchzoo/engine/base_preprocessor.py
matchzoo/engine/base_task.py
matchzoo/engine/hyper_spaces.py
matchzoo/engine/param.py
matchzoo/engine/param_table.py
matchzoo/losses/__init__.py
matchzoo/losses/rank_cross_entropy_loss.py
matchzoo/losses/rank_hinge_loss.py
matchzoo/metrics/__init__.py
matchzoo/metrics/accuracy.py
matchzoo/metrics/average_precision.py
matchzoo/metrics/cross_entropy.py
matchzoo/metrics/discounted_cumulative_gain.py
matchzoo/metrics/mean_average_precision.py
matchzoo/metrics/mean_reciprocal_rank.py
